<?xml version="1.0" encoding="ISO-8859-1"?>
<TRIAL ID="38" GENDER="m" AGE="20" DURATION="4.20">
	<CONTEXT ID ="abs1" REFERENCE-TYPE ="fully-spec" MINIMAL ="no" LENGTH ="3" WORD-STRING ="você deve olhar para o objeto com o quadrado branco">
		<ATTRIBUTE-SET>
			<ATTRIBUTE NAME="type" VALUE="object" />
			<ATTRIBUTE NAME="next" VALUE="q2" />
			<ATTRIBUTE NAME="landmark-type" VALUE="box" />
			<ATTRIBUTE NAME="landmark-others" VALUE="white" />
		</ATTRIBUTE-SET>
	</CONTEXT>
	<CONTEXT ID ="abs3" REFERENCE-TYPE ="fully-spec" MINIMAL ="no" LENGTH ="5" WORD-STRING ="objeto com estrela, circulo e quadrado brancos">
		<ATTRIBUTE-SET>
			<ATTRIBUTE NAME="type" VALUE="star" />
			<ATTRIBUTE NAME="next" VALUE="q1-c1" />
			<ATTRIBUTE NAME="landmark-type" VALUE="box" />
			<ATTRIBUTE NAME="landmark-others" VALUE="white" />
			<ATTRIBUTE NAME="second-landmark-type" VALUE="circle" />
			<ATTRIBUTE NAME="second-landmark-others" VALUE="white" />
		</ATTRIBUTE-SET>
	</CONTEXT>
	<CONTEXT ID ="abs5" REFERENCE-TYPE ="fully-spec" MINIMAL ="no" LENGTH ="4" WORD-STRING ="você deve olhar para o objeto estrela , quadrado branco e circulo">
		<ATTRIBUTE-SET>
			<ATTRIBUTE NAME="type" VALUE="star" />
			<ATTRIBUTE NAME="next" VALUE="q6-c2" />
			<ATTRIBUTE NAME="landmark-type" VALUE="box" />
			<ATTRIBUTE NAME="landmark-others" VALUE="white" />
			<ATTRIBUTE NAME="second-landmark-type" VALUE="circle" />
		</ATTRIBUTE-SET>
	</CONTEXT>
	<CONTEXT ID ="fill1" REFERENCE-TYPE ="na" MINIMAL ="na" LENGTH ="4" WORD-STRING ="você deve olhar para a estrela, seguida do quadrado , seguida do círculo vermelho">
		<ATTRIBUTE-SET>
			<ATTRIBUTE NAME="type" VALUE="star" />
			<ATTRIBUTE NAME="next" VALUE="c3-q1" />
			<ATTRIBUTE NAME="landmark-type" VALUE="box" />
			<ATTRIBUTE NAME="second-landmark-type" VALUE="circle" />
			<ATTRIBUTE NAME="second-landmark-others" VALUE="red" />
		</ATTRIBUTE-SET>
	</CONTEXT>
	<CONTEXT ID ="fill2" REFERENCE-TYPE ="na" MINIMAL ="na" LENGTH ="5" WORD-STRING ="para a estrela , seguida do quadrado vermelho e circulo branco">
		<ATTRIBUTE-SET>
			<ATTRIBUTE NAME="type" VALUE="star" />
			<ATTRIBUTE NAME="next" VALUE="c1-q3" />
			<ATTRIBUTE NAME="landmark-type" VALUE="box" />
			<ATTRIBUTE NAME="landmark-others" VALUE="red" />
			<ATTRIBUTE NAME="second-landmark-type" VALUE="circle" />
			<ATTRIBUTE NAME="second-landmark-others" VALUE="white" />
		</ATTRIBUTE-SET>
	</CONTEXT>
	<CONTEXT ID ="fill3" REFERENCE-TYPE ="na" MINIMAL ="na" LENGTH ="6" WORD-STRING ="você deve olhar para a estrela e quadrado e circunferência, todos brancos">
		<ATTRIBUTE-SET>
			<ATTRIBUTE NAME="type" VALUE="star" />
			<ATTRIBUTE NAME="others" VALUE="white" />
			<ATTRIBUTE NAME="next" VALUE="c1-q6" />
			<ATTRIBUTE NAME="landmark-type" VALUE="box" />
			<ATTRIBUTE NAME="landmark-others" VALUE="white" />
			<ATTRIBUTE NAME="second-landmark-type" VALUE="circle" />
			<ATTRIBUTE NAME="second-landmark-others" VALUE="white" />
		</ATTRIBUTE-SET>
	</CONTEXT>
	<CONTEXT ID ="fill4" REFERENCE-TYPE ="na" MINIMAL ="na" LENGTH ="5" WORD-STRING ="você deve olhar para a estrela seguida do circulo branco e circunferência branca">
		<ATTRIBUTE-SET>
			<ATTRIBUTE NAME="type" VALUE="star" />
			<ATTRIBUTE NAME="next" VALUE="c2-q1" />
			<ATTRIBUTE NAME="landmark-type" VALUE="box" />
			<ATTRIBUTE NAME="landmark-others" VALUE="white" />
			<ATTRIBUTE NAME="second-landmark-type" VALUE="circle" />
			<ATTRIBUTE NAME="second-landmark-others" VALUE="white" />
		</ATTRIBUTE-SET>
	</CONTEXT>
	<CONTEXT ID ="fill5" REFERENCE-TYPE ="na" MINIMAL ="na" LENGTH ="6" WORD-STRING ="para a estrela , seguida do quadrado , seguida do circulo todos brancos">
		<ATTRIBUTE-SET>
			<ATTRIBUTE NAME="type" VALUE="star" />
			<ATTRIBUTE NAME="others" VALUE="white" />
			<ATTRIBUTE NAME="next" VALUE="c2-q2" />
			<ATTRIBUTE NAME="landmark-type" VALUE="box" />
			<ATTRIBUTE NAME="landmark-others" VALUE="white" />
			<ATTRIBUTE NAME="second-landmark-type" VALUE="circle" />
			<ATTRIBUTE NAME="second-landmark-others" VALUE="white" />
		</ATTRIBUTE-SET>
	</CONTEXT>
	<CONTEXT ID ="proj1" REFERENCE-TYPE ="under-spec" MINIMAL ="no" LENGTH ="4" WORD-STRING ="você deve olhar para a estrela seguida do círculo, seguida do quadrado e circunferência branca mais afastada do corpo">
		<ATTRIBUTE-SET>
			<ATTRIBUTE NAME="type" VALUE="star" />
			<ATTRIBUTE NAME="next" VALUE="q1-c1" />
			<ATTRIBUTE NAME="landmark-type" VALUE="box" />
			<ATTRIBUTE NAME="second-landmark-type" VALUE="circle" />
			<ATTRIBUTE NAME="second-landmark-others" VALUE="white,distant" />
		</ATTRIBUTE-SET>
	</CONTEXT>
	<CONTEXT ID ="proj3" REFERENCE-TYPE ="under-spec" MINIMAL ="no" LENGTH ="3" WORD-STRING ="você deve olhar para o objeto com estrela quadrado e circulo seguidos">
		<ATTRIBUTE-SET>
			<ATTRIBUTE NAME="type" VALUE="star" />
			<ATTRIBUTE NAME="next" VALUE="q4-c2" />
			<ATTRIBUTE NAME="landmark-type" VALUE="box" />
			<ATTRIBUTE NAME="second-landmark-type" VALUE="circle" />
		</ATTRIBUTE-SET>
	</CONTEXT>
	<CONTEXT ID ="proj5" REFERENCE-TYPE ="under-spec" MINIMAL ="no" LENGTH ="3" WORD-STRING ="você deve olhar para a estrela seguida do quadrado e o circulo mais afastado">
		<ATTRIBUTE-SET>
			<ATTRIBUTE NAME="type" VALUE="star" />
			<ATTRIBUTE NAME="next" VALUE="q6-c2" />
			<ATTRIBUTE NAME="landmark-type" VALUE="box" />
			<ATTRIBUTE NAME="second-landmark-type" VALUE="circle" />
			<ATTRIBUTE NAME="second-landmark-others" VALUE="distant" />
		</ATTRIBUTE-SET>
	</CONTEXT>
</TRIAL>